cookiecutter.json
fulmo_cookiecutter_poetry/__init__.py
fulmo_cookiecutter_poetry/cli.py
hooks/__init__.py
hooks/post_gen_project.py
hooks/pre_gen_project.py
{{cookiecutter.project_name}}/.editorconfig
{{cookiecutter.project_name}}/.github/actions/setup-poetry-env/action.yml
{{cookiecutter.project_name}}/.github/workflows/main.yml
{{cookiecutter.project_name}}/.github/workflows/on-release-main.yml
{{cookiecutter.project_name}}/.github/workflows/validate-codecov-config.yml
{{cookiecutter.project_name}}/.gitignore
{{cookiecutter.project_name}}/.pre-commit-config.yaml
{{cookiecutter.project_name}}/CONTRIBUTING.md
{{cookiecutter.project_name}}/LICENSE
{{cookiecutter.project_name}}/Makefile
{{cookiecutter.project_name}}/README.md
{{cookiecutter.project_name}}/codecov.yaml
{{cookiecutter.project_name}}/docs/index.md
{{cookiecutter.project_name}}/docs/modules.md
{{cookiecutter.project_name}}/duties.py
{{cookiecutter.project_name}}/mkdocs.yml
{{cookiecutter.project_name}}/poetry.toml
{{cookiecutter.project_name}}/pyproject.toml
{{cookiecutter.project_name}}/tests/__init__.py
{{cookiecutter.project_name}}/tests/test_cli.py
{{cookiecutter.project_name}}/tox.ini
{{cookiecutter.project_name}}/{{cookiecutter.project_slug}}/__init__.py
{{cookiecutter.project_name}}/{{cookiecutter.project_slug}}/cli.py
{{cookiecutter.project_name}}/{{cookiecutter.project_slug}}/{{cookiecutter.project_slug}}.py
fulmo_cookiecutter_poetry-0.4.2.dist-info/LICENSE
fulmo_cookiecutter_poetry-0.4.2.dist-info/WHEEL
fulmo_cookiecutter_poetry-0.4.2.dist-info/METADATA
fulmo_cookiecutter_poetry-0.4.2.dist-info/entry_points.txt
fulmo_cookiecutter_poetry-0.4.2.dist-info/RECORD
