Metadata-Version: 2.1
Name: fulmo-cookiecutter-poetry
Version: 0.4.2
Summary: A python cookiecutter application to create a new python project that uses poetry to manage its dependencies.
Home-page: https://github.com/jexio/cookiecutter-poetry
License: MIT
Author: Gleb Glushkov
Author-email: ptjexio@gmail.com
Requires-Python: >=3.10,<4.0
Classifier: Development Status :: 4 - Beta
Classifier: Environment :: Console
Classifier: Intended Audience :: Developers
Classifier: License :: OSI Approved :: MIT License
Classifier: Natural Language :: English
Classifier: Programming Language :: Python :: 3
Classifier: Programming Language :: Python :: 3.10
Classifier: Programming Language :: Python :: 3.11
Classifier: Programming Language :: Python :: 3 :: Only
Classifier: Programming Language :: Python :: 3.10
Classifier: Programming Language :: Python :: 3.11
Classifier: Topic :: Software Development
Requires-Dist: cookiecutter (>=2.1.1,<3.0.0)
Project-URL: Documentation, https://jexio.github.io/cookiecutter-poetry/
Project-URL: Repository, https://github.com/jexio/cookiecutter-poetry
